xmci/__init__.py
xmci/metrics.py
xmci-0.0.35.dist-info/METADATA
xmci-0.0.35.dist-info/WHEEL
xmci-0.0.35.dist-info/licenses/LICENSE
xmci-0.0.35.dist-info/RECORD
