Metadata-Version: 2.3
Name: xmci
Version: 0.0.35
Summary: XMPro Control Insight is a Python library designed for monitoring and analyzing industrial control loops using various performance metrics. This package provides an easy-to-use framework to measure key performance indicators (KPIs) related to control systems and identify potential issues such as saturation, tuning problems, and disturbances.
Project-URL: Homepage, https://github.com/pypa/sampleproject
Project-URL: Issues, https://github.com/pypa/sampleproject/issues
Author-email: Jaun van Heerden <jvh@xmpro.com>, Zhayne Figueroa <zf@xmpro.com>
License-File: LICENSE
Classifier: License :: OSI Approved :: MIT License
Classifier: Operating System :: OS Independent
Classifier: Programming Language :: Python :: 3
Requires-Python: >=3.8
Requires-Dist: numpy
